asciipal/__init__.py
asciipal/main.py
asciipal-0.0.2.dist-info/licenses/LICENSE.txt
asciipal-0.0.2.dist-info/METADATA
asciipal-0.0.2.dist-info/WHEEL
asciipal-0.0.2.dist-info/entry_points.txt
asciipal-0.0.2.dist-info/top_level.txt
asciipal-0.0.2.dist-info/RECORD
